ai_coder/__init__.py
ai_coder/model.py
aicoderx-0.1.7.dist-info/licenses/LICENSE
aicoderx-0.1.7.dist-info/METADATA
aicoderx-0.1.7.dist-info/WHEEL
aicoderx-0.1.7.dist-info/top_level.txt
aicoderx-0.1.7.dist-info/RECORD
