Metadata-Version: 2.4
Name: aicoderx
Version: 0.1.7
Summary: Lightweight code generation using quantized LLMs
Home-page: https://github.com/jayyvk/ai-coder
Author: Jay Kilaparthi
Author-email: Jayakeerth Kilaparthi <jayakeerth@example.com>
License: MIT
Requires-Python: >=3.8
License-File: LICENSE
Requires-Dist: transformers
Requires-Dist: torch
Requires-Dist: accelerate
Dynamic: author
Dynamic: home-page
Dynamic: license-file
Dynamic: requires-python
